{"formatVersion":"1.0","generatedAt":"2024-09-22T08:46:41Z","keywords":["swift","python","kivy"],"name":"Kivy Packages","overview":"Kivy Swift packages","packages":[{"keywords":[],"url":"https://github.com/KivySwiftPackages/PyAdMob.git","versions":[{"defaultToolsVersion":"5.9","manifests":{"5.9":{"minimumPlatformVersions":[{"name":"ios","version":"13.0"}],"packageName":"PyAdmob","products":[{"name":"PyAdmob","targets":["PyAdmob"],"type":{"library":["automatic"]}}],"targets":[{"moduleName":"PyAdmob","name":"PyAdmob"}],"toolsVersion":"5.9"}},"version":"311.0.0"},{"defaultToolsVersion":"5.9","manifests":{"5.9":{"minimumPlatformVersions":[{"name":"ios","version":"13.0"}],"packageName":"PyAdmob","products":[{"name":"PyAdmob","targets":["PyAdmob"],"type":{"library":["automatic"]}}],"targets":[{"moduleName":"PyAdmob","name":"PyAdmob"}],"toolsVersion":"5.9"}},"version":"310.0.1"},{"defaultToolsVersion":"5.9","manifests":{"5.9":{"minimumPlatformVersions":[{"name":"ios","version":"13.0"}],"packageName":"PyAdmob","products":[{"name":"PyAdmob","targets":["PyAdmob"],"type":{"library":["automatic"]}}],"targets":[{"moduleName":"PyAdmob","name":"PyAdmob"}],"toolsVersion":"5.9"}},"version":"310.0.0"}]},{"keywords":[],"license":{"name":"GPL-3.0","url":"https://raw.githubusercontent.com/KivySwiftPackages/PyCamera/main/LICENSE"},"readmeURL":"https://raw.githubusercontent.com/KivySwiftPackages/PyCamera/main/README.md","url":"https://github.com/KivySwiftPackages/PyCamera.git","versions":[{"defaultToolsVersion":"5.8","manifests":{"5.8":{"minimumPlatformVersions":[{"name":"ios","version":"13.0"}],"packageName":"PyCamera","products":[{"name":"PyCamera","targets":["PyCamera"],"type":{"library":["automatic"]}}],"targets":[{"moduleName":"PyCamera","name":"PyCamera"}],"toolsVersion":"5.8"}},"version":"311.0.0"},{"defaultToolsVersion":"5.8","manifests":{"5.8":{"minimumPlatformVersions":[{"name":"ios","version":"13.0"}],"packageName":"PyCamera","products":[{"name":"PyCamera","targets":["PyCamera"],"type":{"library":["automatic"]}}],"targets":[{"moduleName":"PyCamera","name":"PyCamera"}],"toolsVersion":"5.8"}},"version":"310.0.0"}]},{"keywords":[],"license":{"name":"GPL-3.0","url":"https://raw.githubusercontent.com/KivySwiftPackages/PyCoreBluetooth/master/LICENSE"},"readmeURL":"https://raw.githubusercontent.com/KivySwiftPackages/PyCoreBluetooth/master/README.md","url":"https://github.com/KivySwiftPackages/PyCoreBluetooth.git","versions":[{"defaultToolsVersion":"5.8","manifests":{"5.8":{"minimumPlatformVersions":[{"name":"ios","version":"13.0"}],"packageName":"PyCoreBluetooth","products":[{"name":"PyCoreBluetooth","targets":["PyCoreBluetooth"],"type":{"library":["automatic"]}}],"targets":[{"moduleName":"PyCoreBluetooth","name":"PyCoreBluetooth"}],"toolsVersion":"5.8"}},"version":"311.0.0"},{"defaultToolsVersion":"5.8","manifests":{"5.8":{"minimumPlatformVersions":[{"name":"ios","version":"13.0"}],"packageName":"PyCoreBluetooth","products":[{"name":"PyCoreBluetooth","targets":["PyCoreBluetooth"],"type":{"library":["automatic"]}}],"targets":[{"moduleName":"PyCoreBluetooth","name":"PyCoreBluetooth"}],"toolsVersion":"5.8"}},"version":"310.0.2"},{"defaultToolsVersion":"5.8","manifests":{"5.8":{"minimumPlatformVersions":[{"name":"ios","version":"13.0"}],"packageName":"PyCoreBluetooth","products":[{"name":"PyCoreBluetooth","targets":["PyCoreBluetooth"],"type":{"library":["automatic"]}}],"targets":[{"moduleName":"PyCoreBluetooth","name":"PyCoreBluetooth"}],"toolsVersion":"5.8"}},"version":"310.0.1"},{"defaultToolsVersion":"5.9","manifests":{"5.9":{"minimumPlatformVersions":[{"name":"ios","version":"13.0"}],"packageName":"PyCoreBluetooth","products":[{"name":"PyCoreBluetooth","targets":["PyCoreBluetooth"],"type":{"library":["automatic"]}}],"targets":[{"moduleName":"PyCoreBluetooth","name":"PyCoreBluetooth"}],"toolsVersion":"5.9"}},"version":"310.0.0"}]},{"keywords":[],"license":{"name":"GPL-3.0","url":"https://raw.githubusercontent.com/KivySwiftPackages/PyCoreVideo/main/LICENSE"},"readmeURL":"https://raw.githubusercontent.com/KivySwiftPackages/PyCoreVideo/main/README.md","url":"https://github.com/KivySwiftPackages/PyCoreVideo.git","versions":[{"defaultToolsVersion":"5.8","manifests":{"5.8":{"minimumPlatformVersions":[{"name":"ios","version":"13.0"}],"packageName":"PyCoreVideo","products":[{"name":"PyCoreVideo","targets":["PyCoreVideo"],"type":{"library":["automatic"]}}],"targets":[{"moduleName":"PyCoreVideo","name":"PyCoreVideo"}],"toolsVersion":"5.8"}},"version":"311.0.0"},{"defaultToolsVersion":"5.8","manifests":{"5.8":{"minimumPlatformVersions":[{"name":"ios","version":"13.0"}],"packageName":"PyCoreVideo","products":[{"name":"PyCoreVideo","targets":["PyCoreVideo"],"type":{"library":["automatic"]}}],"targets":[{"moduleName":"PyCoreVideo","name":"PyCoreVideo"}],"toolsVersion":"5.8"}},"version":"310.0.0"}]},{"keywords":[],"license":{"name":"GPL-3.0","url":"https://raw.githubusercontent.com/KivySwiftPackages/PyFoundation/main/LICENSE"},"readmeURL":"https://raw.githubusercontent.com/KivySwiftPackages/PyFoundation/main/README.md","url":"https://github.com/KivySwiftPackages/PyFoundation.git","versions":[{"defaultToolsVersion":"5.8","manifests":{"5.8":{"minimumPlatformVersions":[{"name":"ios","version":"13.0"}],"packageName":"PyFoundation","products":[{"name":"PyFoundation","targets":["PyFoundation"],"type":{"library":["automatic"]}}],"targets":[{"moduleName":"PyFoundation","name":"PyFoundation"}],"toolsVersion":"5.8"}},"version":"311.0.0"},{"defaultToolsVersion":"5.8","manifests":{"5.8":{"minimumPlatformVersions":[{"name":"ios","version":"13.0"}],"packageName":"PyFoundation","products":[{"name":"PyFoundation","targets":["PyFoundation"],"type":{"library":["automatic"]}}],"targets":[{"moduleName":"PyFoundation","name":"PyFoundation"}],"toolsVersion":"5.8"}},"version":"310.0.1"},{"defaultToolsVersion":"5.8","manifests":{"5.8":{"minimumPlatformVersions":[{"name":"ios","version":"13.0"}],"packageName":"PyFoundation","products":[{"name":"PyFoundation","targets":["PyFoundation"],"type":{"library":["automatic"]}}],"targets":[{"moduleName":"PyFoundation","name":"PyFoundation"}],"toolsVersion":"5.8"}},"version":"310.0.0"}]},{"keywords":[],"readmeURL":"https://raw.githubusercontent.com/KivySwiftPackages/PyOpenCV/main/README.md","url":"https://github.com/KivySwiftPackages/PyOpenCV.git","versions":[{"defaultToolsVersion":"5.7","manifests":{"5.7":{"minimumPlatformVersions":[{"name":"ios","version":"13.0"}],"packageName":"PyOpenCV","products":[{"name":"PyOpenCV","targets":["PyOpenCV"],"type":{"library":["automatic"]}}],"targets":[{"moduleName":"PyOpenCV","name":"PyOpenCV"}],"toolsVersion":"5.7"}},"version":"310.0.0"}]},{"keywords":[],"license":{"name":"GPL-3.0","url":"https://raw.githubusercontent.com/KivySwiftPackages/PyPHPicker/main/LICENSE"},"readmeURL":"https://raw.githubusercontent.com/KivySwiftPackages/PyPHPicker/main/README.md","url":"https://github.com/KivySwiftPackages/PyPHPicker.git","versions":[{"defaultToolsVersion":"5.8","manifests":{"5.8":{"minimumPlatformVersions":[{"name":"ios","version":"14.0"}],"packageName":"PyPHPicker","products":[{"name":"PyPHPicker","targets":["PyPHPicker"],"type":{"library":["automatic"]}}],"targets":[{"moduleName":"PyPHPicker","name":"PyPHPicker"}],"toolsVersion":"5.8"}},"version":"311.0.0"},{"defaultToolsVersion":"5.8","manifests":{"5.8":{"minimumPlatformVersions":[{"name":"ios","version":"14.0"}],"packageName":"PyPHPicker","products":[{"name":"PyPHPicker","targets":["PyPHPicker"],"type":{"library":["automatic"]}}],"targets":[{"moduleName":"PyPHPicker","name":"PyPHPicker"}],"toolsVersion":"5.8"}},"version":"310.0.0"}]},{"keywords":[],"license":{"name":"GPL-3.0","url":"https://raw.githubusercontent.com/KivySwiftPackages/PySpeechRecognizer/main/LICENSE"},"readmeURL":"https://raw.githubusercontent.com/KivySwiftPackages/PySpeechRecognizer/main/README.md","url":"https://github.com/KivySwiftPackages/PySpeechRecognizer.git","versions":[{"defaultToolsVersion":"5.8","manifests":{"5.8":{"minimumPlatformVersions":[{"name":"ios","version":"14.0"}],"packageName":"PySpeechRecognizer","products":[{"name":"PySpeechRecognizer","targets":["PySpeechRecognizer"],"type":{"library":["automatic"]}}],"targets":[{"moduleName":"PySpeechRecognizer","name":"PySpeechRecognizer"}],"toolsVersion":"5.8"}},"version":"311.0.1"},{"defaultToolsVersion":"5.8","manifests":{"5.8":{"minimumPlatformVersions":[{"name":"ios","version":"14.0"}],"packageName":"PySpeechRecognizer","products":[{"name":"PySpeechRecognizer","targets":["PySpeechRecognizer"],"type":{"library":["automatic"]}}],"targets":[{"moduleName":"PySpeechRecognizer","name":"PySpeechRecognizer"}],"toolsVersion":"5.8"}},"version":"311.0.0"},{"defaultToolsVersion":"5.8","manifests":{"5.8":{"minimumPlatformVersions":[{"name":"ios","version":"14.0"}],"packageName":"PySpeechRecognizer","products":[{"name":"PySpeechRecognizer","targets":["PySpeechRecognizer"],"type":{"library":["automatic"]}}],"targets":[{"moduleName":"PySpeechRecognizer","name":"PySpeechRecognizer"}],"toolsVersion":"5.8"}},"version":"310.0.0"}]},{"keywords":[],"license":{"name":"GPL-3.0","url":"https://raw.githubusercontent.com/KivySwiftPackages/PyTextToSpeech/main/LICENSE"},"readmeURL":"https://raw.githubusercontent.com/KivySwiftPackages/PyTextToSpeech/main/README.md","url":"https://github.com/KivySwiftPackages/PyTextToSpeech.git","versions":[{"defaultToolsVersion":"5.8","manifests":{"5.8":{"minimumPlatformVersions":[{"name":"ios","version":"13.0"}],"packageName":"PyTextToSpeech","products":[{"name":"PyTextToSpeech","targets":["PyTextToSpeech"],"type":{"library":["automatic"]}}],"targets":[{"moduleName":"PyTextToSpeech","name":"PyTextToSpeech"}],"toolsVersion":"5.8"}},"version":"311.0.1"},{"defaultToolsVersion":"5.8","manifests":{"5.8":{"minimumPlatformVersions":[{"name":"ios","version":"13.0"}],"packageName":"PyTextToSpeech","products":[{"name":"PyTextToSpeech","targets":["PyTextToSpeech"],"type":{"library":["automatic"]}}],"targets":[{"moduleName":"PyTextToSpeech","name":"PyTextToSpeech"}],"toolsVersion":"5.8"}},"version":"311.0.0"},{"defaultToolsVersion":"5.8","manifests":{"5.8":{"minimumPlatformVersions":[{"name":"ios","version":"13.0"}],"packageName":"PyTextToSpeech","products":[{"name":"PyTextToSpeech","targets":["PyTextToSpeech"],"type":{"library":["automatic"]}}],"targets":[{"moduleName":"PyTextToSpeech","name":"PyTextToSpeech"}],"toolsVersion":"5.8"}},"version":"310.0.0"}]},{"keywords":[],"license":{"name":"GPL-3.0","url":"https://raw.githubusercontent.com/KivySwiftPackages/PyWebViews/main/LICENSE"},"readmeURL":"https://raw.githubusercontent.com/KivySwiftPackages/PyWebViews/main/README.md","url":"https://github.com/KivySwiftPackages/PyWebViews.git","versions":[{"defaultToolsVersion":"5.8","manifests":{"5.8":{"minimumPlatformVersions":[{"name":"ios","version":"13.0"}],"packageName":"PyWebViews","products":[{"name":"PyWebViews","targets":["PyWebViews"],"type":{"library":["automatic"]}}],"targets":[{"moduleName":"PyWebViews","name":"PyWebViews"}],"toolsVersion":"5.8"}},"version":"311.0.0"},{"defaultToolsVersion":"5.8","manifests":{"5.8":{"minimumPlatformVersions":[{"name":"ios","version":"13.0"}],"packageName":"PyWebViews","products":[{"name":"PyWebViews","targets":["PyWebViews"],"type":{"library":["automatic"]}}],"targets":[{"moduleName":"PyWebViews","name":"PyWebViews"}],"toolsVersion":"5.8"}},"version":"310.0.0"}]}]}